{
  "placeholderImages": [
    {
      "id": "toyota",
      "description": "Logo of Toyota",
      "imageUrl": "/logos/toyota.svg",
      "imageHint": "car brand logo Toyota"
    },
    {
      "id": "honda",
      "description": "Logo of Honda",
      "imageUrl": "/logos/honda.svg",
      "imageHint": "car brand logo Honda"
    },
    {
      "id": "nissan",
      "description": "Logo of Nissan",
      "imageUrl": "/logos/nissan.svg",
      "imageHint": "car brand logo Nissan"
    },
    {
      "id": "mazda",
      "description": "Logo of Mazda",
      "imageUrl": "/logos/mazda.svg",
      "imageHint": "car brand logo Mazda"
    },
    {
      "id": "subaru",
      "description": "Logo of Subaru",
      "imageUrl": "/logos/subaru.svg",
      "imageHint": "car brand logo Subaru"
    },
    {
      "id": "mitsubishi",
      "description": "Logo of Mitsubishi",
      "imageUrl": "/logos/mitsubishi.svg",
      "imageHint": "car brand logo Mitsubishi"
    },
    {
      "id": "suzuki",
      "description": "Logo of Suzuki",
      "imageUrl": "/logos/suzuki.svg",
      "imageHint": "car brand logo Suzuki"
    },
    {
      "id": "lexus",
      "description": "Logo of Lexus",
      "imageUrl": "/logos/lexus.svg",
      "imageHint": "car brand logo Lexus"
    },
    {
      "id": "bmw",
      "description": "Logo of BMW",
      "imageUrl": "/logos/bmw.svg",
      "imageHint": "car brand logo BMW"
    },
    {
      "id": "mercedes",
      "description": "Logo of Mercedes-Benz",
      "imageUrl": "/logos/mercedes.svg",
      "imageHint": "car brand logo Mercedes-Benz"
    },
    {
      "id": "audi",
      "description": "Logo of Audi",
      "imageUrl": "/logos/audi.svg",
      "imageHint": "car brand logo Audi"
    },
    {
      "id": "volkswagen",
      "description": "Logo of Volkswagen",
      "imageUrl": "/logos/volkswagen.svg",
      "imageHint": "car brand logo Volkswagen"
    },
    {
      "id": "porsche",
      "description": "Logo of Porsche",
      "imageUrl": "/logos/porsche.svg",
      "imageHint": "car brand logo Porsche"
    },
    {
      "id": "opel",
      "description": "Logo of Opel",
      "imageUrl": "/logos/opel.svg",
      "imageHint": "car brand logo Opel"
    },
    {
      "id": "ford",
      "description": "Logo of Ford",
      "imageUrl": "/logos/ford.svg",
      "imageHint": "car brand logo Ford"
    },
    {
      "id": "chevrolet",
      "description": "Logo of Chevrolet",
      "imageUrl": "/logos/chevrolet.svg",
      "imageHint": "car brand logo Chevrolet"
    },
    {
      "id": "tesla",
      "description": "Logo of Tesla",
      "imageUrl": "/logos/tesla.svg",
      "imageHint": "car brand logo Tesla"
    },
    {
      "id": "jeep",
      "description": "Logo of Jeep",
      "imageUrl": "/logos/jeep.svg",
      "imageHint": "car brand logo Jeep"
    },
    {
      "id": "dodge",
      "description": "Logo of Dodge",
      "imageUrl": "/logos/dodge.svg",
      "imageHint": "car brand logo Dodge"
    },
    {
      "id": "cadillac",
      "description": "Logo of Cadillac",
      "imageUrl": "/logos/cadillac.svg",
      "imageHint": "car brand logo Cadillac"
    },
    {
      "id": "hyundai",
      "description": "Logo of Hyundai",
      "imageUrl": "/logos/hyundai.svg",
      "imageHint": "car brand logo Hyundai"
    },
    {
      "id": "kia",
      "description": "Logo of Kia",
      "imageUrl": "/logos/kia.svg",
      "imageHint": "car brand logo Kia"
    },
    {
      "id": "volvo",
      "description": "Logo of Volvo",
      "imageUrl": "/logos/volvo.svg",
      "imageHint": "car brand logo Volvo"
    },
    {
      "id": "peugeot",
      "description": "Logo of Peugeot",
      "imageUrl": "/logos/peugeot.svg",
      "imageHint": "car brand logo Peugeot"
    },
    {
      "id": "renault",
      "description": "Logo of Renault",
      "imageUrl": "/logos/renault.svg",
      "imageHint": "car brand logo Renault"
    },
    {
      "id": "citroen",
      "description": "Logo of Citroen",
      "imageUrl": "/logos/citroen.svg",
      "imageHint": "car brand logo Citroen"
    },
    {
      "id": "fiat",
      "description": "Logo of Fiat",
      "imageUrl": "/logos/fiat.svg",
      "imageHint": "car brand logo Fiat"
    },
    {
      "id": "ferrari",
      "description": "Logo of Ferrari",
      "imageUrl": "/logos/ferrari.svg",
      "imageHint": "car brand logo Ferrari"
    },
    {
      "id": "lamborghini",
      "description": "Logo of Lamborghini",
      "imageUrl": "/logos/lamborghini.svg",
      "imageHint": "car brand logo Lamborghini"
    },
    {
      "id": "alfaromeo",
      "description": "Logo of Alfa Romeo",
      "imageUrl": "/logos/alfaromeo.svg",
      "imageHint": "car brand logo Alfa Romeo"
    },
    {
      "id": "skoda",
      "description": "Logo of Skoda",
      "imageUrl": "/logos/skoda.svg",
      "imageHint": "car brand logo Skoda"
    },
    {
      "id": "seat",
      "description": "Logo of SEAT",
      "imageUrl": "/logos/seat.svg",
      "imageHint": "car brand logo SEAT"
    },
    {
      "id": "jaguar",
      "description": "Logo of Jaguar",
      "imageUrl": "/logos/jaguar.svg",
      "imageHint": "car brand logo Jaguar"
    },
    {
      "id": "landrover",
      "description": "Logo of Land Rover",
      "imageUrl": "/logos/landrover.svg",
      "imageHint": "car brand logo Land Rover"
    },
    {
      "id": "mini",
      "description": "Logo of MINI",
      "imageUrl": "/logos/mini.svg",
      "imageHint": "car brand logo MINI"
    }
  ]
}